econci/__init__.py
econci/complexity.py
econci/utils.py
econci-0.1.3.dist-info/LICENSE
econci-0.1.3.dist-info/WHEEL
econci-0.1.3.dist-info/METADATA
econci-0.1.3.dist-info/RECORD
