Metadata-Version: 2.1
Name: econci
Version: 0.1.3
Summary: 
License: MIT
Author: phcsoares
Author-email: phcastrosoares@gmail.com
Requires-Python: >=3.8,<4.0
Classifier: License :: OSI Approved :: MIT License
Classifier: Programming Language :: Python :: 3
Classifier: Programming Language :: Python :: 3.10
Classifier: Programming Language :: Python :: 3.8
Classifier: Programming Language :: Python :: 3.9
Requires-Dist: networkx (>=2.4)
Requires-Dist: pandas (>=0.25.0)
